nmaptocsv/__init__.py
nmaptocsv/nmaptocsv.py
secsi_nmaptocsv-1.7.1.dist-info/METADATA
secsi_nmaptocsv-1.7.1.dist-info/WHEEL
secsi_nmaptocsv-1.7.1.dist-info/entry_points.txt
secsi_nmaptocsv-1.7.1.dist-info/licenses/COPYING
secsi_nmaptocsv-1.7.1.dist-info/licenses/COPYING.LESSER
secsi_nmaptocsv-1.7.1.dist-info/RECORD
