Metadata-Version: 2.4
Name: secsi-nmaptocsv
Version: 1.7.1
Summary: Convert Nmap XML output to CSV format
Project-URL: Homepage, https://secsi.io
Project-URL: Repository, https://github.com/cybersecsi/nmaptocsv
Author-email: Thomas Debize <tdebize@mail.com>
Maintainer-email: Emanuele Galdi <emanuele.galdi@secsi.io>
License: MIT
License-File: COPYING
License-File: COPYING.LESSER
Keywords: cli,csv,network,nmap,secsi,security,xml
Classifier: Development Status :: 5 - Production/Stable
Classifier: Environment :: Console
Classifier: Intended Audience :: Information Technology
Classifier: Intended Audience :: System Administrators
Classifier: License :: OSI Approved :: MIT License
Classifier: Programming Language :: Python :: 3
Classifier: Topic :: Security
Classifier: Topic :: Utilities
Requires-Python: >=3.7
Requires-Dist: argparse
Requires-Dist: future
